skspatial/__init__.py
skspatial/_functions.py
skspatial/measurement.py
skspatial/plotting.py
skspatial/py.typed
skspatial/transformation.py
skspatial/typing.py
skspatial/objects/__init__.py
skspatial/objects/_base_array.py
skspatial/objects/_base_line_plane.py
skspatial/objects/_base_spatial.py
skspatial/objects/_base_sphere.py
skspatial/objects/_mixins.py
skspatial/objects/circle.py
skspatial/objects/cylinder.py
skspatial/objects/line.py
skspatial/objects/line_segment.py
skspatial/objects/plane.py
skspatial/objects/point.py
skspatial/objects/points.py
skspatial/objects/sphere.py
skspatial/objects/triangle.py
skspatial/objects/vector.py
scikit_spatial-9.0.1.dist-info/METADATA
scikit_spatial-9.0.1.dist-info/WHEEL
scikit_spatial-9.0.1.dist-info/licenses/AUTHORS.rst
scikit_spatial-9.0.1.dist-info/licenses/LICENSE
scikit_spatial-9.0.1.dist-info/RECORD
