Metadata-Version: 2.4
Name: scikit-spatial
Version: 9.0.1
Summary: Spatial objects and computations based on NumPy arrays.
Project-URL: repository, https://github.com/ajhynes7/scikit-spatial
Project-URL: documentation, https://scikit-spatial.readthedocs.io
Author-email: Andrew Hynes <andrewjhynes@gmail.com>
License: BSD-3-Clause
License-File: AUTHORS.rst
License-File: LICENSE
Keywords: NumPy,linear algebra,matplotlib,spatial,visualization
Classifier: Development Status :: 5 - Production/Stable
Classifier: Intended Audience :: Science/Research
Classifier: License :: OSI Approved :: BSD License
Classifier: Natural Language :: English
Classifier: Programming Language :: Python :: 3.8
Classifier: Programming Language :: Python :: 3.9
Classifier: Programming Language :: Python :: 3.10
Classifier: Programming Language :: Python :: 3.11
Classifier: Programming Language :: Python :: 3.12
Classifier: Topic :: Scientific/Engineering
Requires-Python: >=3.8
Requires-Dist: numpy>1.24; python_version >= '3.12'
Requires-Dist: numpy>=1; python_version < '3.12'
Requires-Dist: scipy>1.11; python_version >= '3.12'
Requires-Dist: scipy>=1; python_version < '3.12'
Provides-Extra: plotting
Requires-Dist: matplotlib>=3; extra == 'plotting'
